Metadata-Version: 2.1
Name: opendatalab
Version: 0.0.9
Summary: OpenDataLab Python SDK
Home-page: https://github.com/opendatalab/opendatalab-python-sdk
Author: OpenDataLab
Author-email: OpenDataLab@pjlab.org.cn
License: MIT
Project-URL: Bug Tracker, https://github.com/opendatalab/opendatalab-python-sdk/issues
Keywords: opendatalab,dataset,test
Classifier: Development Status :: 4 - Beta
Classifier: Intended Audience :: Developers
Classifier: Intended Audience :: Science/Research
Classifier: License :: OSI Approved :: MIT License
Classifier: Operating System :: OS Independent
Classifier: Programming Language :: Python
Classifier: Programming Language :: Python :: 3
Classifier: Programming Language :: Python :: 3 :: Only
Classifier: Programming Language :: Python :: 3.7
Classifier: Programming Language :: Python :: 3.8
Classifier: Programming Language :: Python :: 3.9
Classifier: Programming Language :: Python :: 3.10
Classifier: Topic :: Scientific/Engineering :: Artificial Intelligence
Classifier: Typing :: Typed
Requires-Python: >=3.7
License-File: LICENSE
Requires-Dist: pycryptodome
Requires-Dist: click (>=7.0.0)
Requires-Dist: requests (>=2.4.2)
Requires-Dist: tqdm
Requires-Dist: colorama
Requires-Dist: rich
Requires-Dist: pywin32 ; platform_system == "Windows"
